odoo/addons/contract_variable_quantity/README.rst
odoo/addons/contract_variable_quantity/__init__.py
odoo/addons/contract_variable_quantity/__manifest__.py
odoo/addons/contract_variable_quantity/i18n/am.po
odoo/addons/contract_variable_quantity/i18n/ar.po
odoo/addons/contract_variable_quantity/i18n/bg.po
odoo/addons/contract_variable_quantity/i18n/bs.po
odoo/addons/contract_variable_quantity/i18n/ca.po
odoo/addons/contract_variable_quantity/i18n/cs.po
odoo/addons/contract_variable_quantity/i18n/da.po
odoo/addons/contract_variable_quantity/i18n/de.po
odoo/addons/contract_variable_quantity/i18n/el_GR.po
odoo/addons/contract_variable_quantity/i18n/en_GB.po
odoo/addons/contract_variable_quantity/i18n/es.po
odoo/addons/contract_variable_quantity/i18n/es_AR.po
odoo/addons/contract_variable_quantity/i18n/es_CO.po
odoo/addons/contract_variable_quantity/i18n/es_CR.po
odoo/addons/contract_variable_quantity/i18n/es_DO.po
odoo/addons/contract_variable_quantity/i18n/es_EC.po
odoo/addons/contract_variable_quantity/i18n/es_ES.po
odoo/addons/contract_variable_quantity/i18n/es_MX.po
odoo/addons/contract_variable_quantity/i18n/es_PY.po
odoo/addons/contract_variable_quantity/i18n/es_VE.po
odoo/addons/contract_variable_quantity/i18n/et.po
odoo/addons/contract_variable_quantity/i18n/eu.po
odoo/addons/contract_variable_quantity/i18n/fa.po
odoo/addons/contract_variable_quantity/i18n/fi.po
odoo/addons/contract_variable_quantity/i18n/fr.po
odoo/addons/contract_variable_quantity/i18n/fr_CA.po
odoo/addons/contract_variable_quantity/i18n/fr_CH.po
odoo/addons/contract_variable_quantity/i18n/gl.po
odoo/addons/contract_variable_quantity/i18n/gl_ES.po
odoo/addons/contract_variable_quantity/i18n/he.po
odoo/addons/contract_variable_quantity/i18n/hi_IN.po
odoo/addons/contract_variable_quantity/i18n/hr.po
odoo/addons/contract_variable_quantity/i18n/hr_HR.po
odoo/addons/contract_variable_quantity/i18n/hu.po
odoo/addons/contract_variable_quantity/i18n/id.po
odoo11_addon_contract_variable_quantity-11.0.1.2.1.dist-info/DESCRIPTION.rst
odoo11_addon_contract_variable_quantity-11.0.1.2.1.dist-info/METADATA
odoo11_addon_contract_variable_quantity-11.0.1.2.1.dist-info/RECORD
odoo11_addon_contract_variable_quantity-11.0.1.2.1.dist-info/WHEEL
odoo11_addon_contract_variable_quantity-11.0.1.2.1.dist-info/metadata.json
odoo11_addon_contract_variable_quantity-11.0.1.2.1.dist-info/top_level.txt
